gitautobackup.py
gitautobackup-2.0.1.2.dist-info/LICENSE
gitautobackup-2.0.1.2.dist-info/METADATA
gitautobackup-2.0.1.2.dist-info/WHEEL
gitautobackup-2.0.1.2.dist-info/entry_points.txt
gitautobackup-2.0.1.2.dist-info/top_level.txt
gitautobackup-2.0.1.2.dist-info/zip-safe
gitautobackup-2.0.1.2.dist-info/RECORD
