Metadata-Version: 2.1
Name: gitautobackup
Version: 2.0.1.2
Summary: A basic CLI program and python module that allows for quickly making and comming changes to a git repository, along with a few other tools
Author-email: Markus Hammer <107761433+MarkusHammer@users.noreply.github.com>
License: Mozilla Public License Version 2.0
Project-URL: Homepage, https://github.com/MarkusHammer/gitautobackup
Project-URL: Github, https://github.com/MarkusHammer/gitautobackup
Project-URL: Issues, https://github.com/MarkusHammer/gitautobackup/issues
Project-URL: Pull Requests, https://github.com/MarkusHammer/gitautobackup/pulls
Project-URL: Git, https://github.com/MarkusHammer/gitautobackup.git
Keywords: backup,git,commit,managment,tool,devtool,small,simple,development,utility
Classifier: License :: OSI Approved :: Mozilla Public License 2.0 (MPL 2.0)
Classifier: Development Status :: 5 - Production/Stable
Classifier: Environment :: Console
Classifier: Intended Audience :: Developers
Classifier: Typing :: Typed
Classifier: Natural Language :: English
Classifier: Topic :: Software Development :: Version Control
Classifier: Topic :: Software Development :: Version Control :: Git
Classifier: Topic :: System :: Archiving
Classifier: Topic :: System :: Archiving :: Backup
Classifier: Topic :: System :: Software Distribution
Classifier: Topic :: Utilities
Classifier: Programming Language :: Python
Classifier: Programming Language :: Python :: 3
Requires-Python: >=3
License-File: LICENSE
Requires-Dist: pathlib
Requires-Dist: GitPython >=3.1.41
Requires-Dist: typing-extensions ; python_version < "3.8"
Provides-Extra: cli
Requires-Dist: argparse ; extra == 'cli'
Provides-Extra: dev
Requires-Dist: setuptools >=64.0.0 ; extra == 'dev'
Requires-Dist: pip-tools ; extra == 'dev'
Requires-Dist: validate-pyproject[all] ; extra == 'dev'
Requires-Dist: build ; extra == 'dev'
Requires-Dist: twine ; extra == 'dev'
